{
  "db_name": "PostgreSQL",
  "query": "\n                    INSERT INTO \"BikeImage\" (bike_id, path)\n                    VALUES ($1, $2)\n                    RETURNING *\n                ",
  "describe": {
    "columns": [
      {
        "ordinal": 0,
        "name": "id",
        "type_info": "Int8"
      },
      {
        "ordinal": 1,
        "name": "bike_id",
        "type_info": "Int8"
      },
      {
        "ordinal": 2,
        "name": "path",
        "type_info": "Text"
      }
    ],
    "parameters": {
      "Left": [
        "Int8",
        "Text"
      ]
    },
    "nullable": [
      false,
      false,
      false
    ]
  },
  "hash": "630bfbddc62fd13b80a0cc40ada720e061e086f31f8696018bb4af1776a97c51"
}
