{
  "db_name": "PostgreSQL",
  "query": "\n            INSERT INTO \"Bike\" (\n                name,\n                internal_id,\n                model_id,\n                preview,\n                description,\n                year,\n                price,\n                frame,\n                seat_tube_sizes,\n                top_tube_size,\n                height,\n                headset,\n                crankset,\n                bottom_bracket,\n                front_derail,\n                rear_derail,\n                brakes,\n                shifters,\n                brake_levers,\n                saddle,\n                seat_post,\n                hubs,\n                rims,\n                handlebar,\n                stem\n            )\n            SELECT\n                name,\n                internal_id,\n                model_id,\n                NULL,\n                description,\n                year,\n                price,\n                frame,\n                seat_tube_sizes,\n                top_tube_size,\n                height,\n                headset,\n                crankset,\n                bottom_bracket,\n                front_derail,\n                rear_derail,\n                brakes,\n                shifters,\n                brake_levers,\n                saddle,\n                seat_post,\n                hubs,\n                rims,\n                handlebar,\n                stem\n            FROM \"Bike\"\n            WHERE id=$1\n            RETURNING *\n            ",
  "describe": {
    "columns": [
      {
        "ordinal": 0,
        "name": "id",
        "type_info": "Int8",
        "origin": {
          "Table": {
            "table": "\"Bike\"",
            "name": "id"
          }
        }
      },
      {
        "ordinal": 1,
        "name": "model_id",
        "type_info": "Int8",
        "origin": {
          "Table": {
            "table": "\"Bike\"",
            "name": "model_id"
          }
        }
      },
      {
        "ordinal": 2,
        "name": "name",
        "type_info": "Text",
        "origin": {
          "Table": {
            "table": "\"Bike\"",
            "name": "name"
          }
        }
      },
      {
        "ordinal": 3,
        "name": "preview",
        "type_info": "Int8",
        "origin": {
          "Table": {
            "table": "\"Bike\"",
            "name": "preview"
          }
        }
      },
      {
        "ordinal": 4,
        "name": "description",
        "type_info": "Text",
        "origin": {
          "Table": {
            "table": "\"Bike\"",
            "name": "description"
          }
        }
      },
      {
        "ordinal": 5,
        "name": "view_count",
        "type_info": "Int8",
        "origin": {
          "Table": {
            "table": "\"Bike\"",
            "name": "view_count"
          }
        }
      },
      {
        "ordinal": 6,
        "name": "like_count",
        "type_info": "Int8",
        "origin": {
          "Table": {
            "table": "\"Bike\"",
            "name": "like_count"
          }
        }
      },
      {
        "ordinal": 7,
        "name": "created_at",
        "type_info": "Timestamptz",
        "origin": {
          "Table": {
            "table": "\"Bike\"",
            "name": "created_at"
          }
        }
      },
      {
        "ordinal": 8,
        "name": "edited_at",
        "type_info": "Timestamptz",
        "origin": {
          "Table": {
            "table": "\"Bike\"",
            "name": "edited_at"
          }
        }
      },
      {
        "ordinal": 9,
        "name": "hidden",
        "type_info": "Bool",
        "origin": {
          "Table": {
            "table": "\"Bike\"",
            "name": "hidden"
          }
        }
      },
      {
        "ordinal": 10,
        "name": "year",
        "type_info": "Int4",
        "origin": {
          "Table": {
            "table": "\"Bike\"",
            "name": "year"
          }
        }
      },
      {
        "ordinal": 11,
        "name": "price",
        "type_info": "Int4",
        "origin": {
          "Table": {
            "table": "\"Bike\"",
            "name": "price"
          }
        }
      },
      {
        "ordinal": 12,
        "name": "frame",
        "type_info": "Text",
        "origin": {
          "Table": {
            "table": "\"Bike\"",
            "name": "frame"
          }
        }
      },
      {
        "ordinal": 13,
        "name": "seat_tube_sizes",
        "type_info": "Text",
        "origin": {
          "Table": {
            "table": "\"Bike\"",
            "name": "seat_tube_sizes"
          }
        }
      },
      {
        "ordinal": 14,
        "name": "top_tube_size",
        "type_info": "Int4",
        "origin": {
          "Table": {
            "table": "\"Bike\"",
            "name": "top_tube_size"
          }
        }
      },
      {
        "ordinal": 15,
        "name": "height",
        "type_info": "Int4",
        "origin": {
          "Table": {
            "table": "\"Bike\"",
            "name": "height"
          }
        }
      },
      {
        "ordinal": 16,
        "name": "headset",
        "type_info": "Text",
        "origin": {
          "Table": {
            "table": "\"Bike\"",
            "name": "headset"
          }
        }
      },
      {
        "ordinal": 17,
        "name": "crankset",
        "type_info": "Text",
        "origin": {
          "Table": {
            "table": "\"Bike\"",
            "name": "crankset"
          }
        }
      },
      {
        "ordinal": 18,
        "name": "bottom_bracket",
        "type_info": "Text",
        "origin": {
          "Table": {
            "table": "\"Bike\"",
            "name": "bottom_bracket"
          }
        }
      },
      {
        "ordinal": 19,
        "name": "front_derail",
        "type_info": "Text",
        "origin": {
          "Table": {
            "table": "\"Bike\"",
            "name": "front_derail"
          }
        }
      },
      {
        "ordinal": 20,
        "name": "rear_derail",
        "type_info": "Text",
        "origin": {
          "Table": {
            "table": "\"Bike\"",
            "name": "rear_derail"
          }
        }
      },
      {
        "ordinal": 21,
        "name": "brakes",
        "type_info": "Text",
        "origin": {
          "Table": {
            "table": "\"Bike\"",
            "name": "brakes"
          }
        }
      },
      {
        "ordinal": 22,
        "name": "shifters",
        "type_info": "Text",
        "origin": {
          "Table": {
            "table": "\"Bike\"",
            "name": "shifters"
          }
        }
      },
      {
        "ordinal": 23,
        "name": "brake_levers",
        "type_info": "Text",
        "origin": {
          "Table": {
            "table": "\"Bike\"",
            "name": "brake_levers"
          }
        }
      },
      {
        "ordinal": 24,
        "name": "saddle",
        "type_info": "Text",
        "origin": {
          "Table": {
            "table": "\"Bike\"",
            "name": "saddle"
          }
        }
      },
      {
        "ordinal": 25,
        "name": "seat_post",
        "type_info": "Text",
        "origin": {
          "Table": {
            "table": "\"Bike\"",
            "name": "seat_post"
          }
        }
      },
      {
        "ordinal": 26,
        "name": "hubs",
        "type_info": "Text",
        "origin": {
          "Table": {
            "table": "\"Bike\"",
            "name": "hubs"
          }
        }
      },
      {
        "ordinal": 27,
        "name": "rims",
        "type_info": "Text",
        "origin": {
          "Table": {
            "table": "\"Bike\"",
            "name": "rims"
          }
        }
      },
      {
        "ordinal": 28,
        "name": "handlebar",
        "type_info": "Text",
        "origin": {
          "Table": {
            "table": "\"Bike\"",
            "name": "handlebar"
          }
        }
      },
      {
        "ordinal": 29,
        "name": "stem",
        "type_info": "Text",
        "origin": {
          "Table": {
            "table": "\"Bike\"",
            "name": "stem"
          }
        }
      },
      {
        "ordinal": 30,
        "name": "status",
        "type_info": "Text",
        "origin": {
          "Table": {
            "table": "\"Bike\"",
            "name": "status"
          }
        }
      },
      {
        "ordinal": 31,
        "name": "internal_id",
        "type_info": "Varchar",
        "origin": {
          "Table": {
            "table": "\"Bike\"",
            "name": "internal_id"
          }
        }
      }
    ],
    "parameters": {
      "Left": [
        "Int8"
      ]
    },
    "nullable": [
      false,
      false,
      false,
      true,
      false,
      false,
      false,
      false,
      false,
      false,
      false,
      false,
      false,
      false,
      false,
      false,
      false,
      false,
      false,
      false,
      false,
      false,
      false,
      false,
      false,
      false,
      false,
      false,
      false,
      false,
      true,
      false
    ]
  },
  "hash": "aa53af1d576019c54bf64bc33c58c48901d08fbd0df65740b347a357e36e5864"
}
